{
  "mapMarkers": [
    {
      "id": "MapCalcExample",
      "lastAccessed": 1755037948237,
      "markers": [
        {
          "id": "ID_b99b2ba81a69",
          "type": "People",
          "loc": [
            512.5234375,
            771.25
          ],
          "link": "Lazarus",
          "layer": "%5B%5BJerusalem.png%5D%5D",
          "mutable": true,
          "command": false,
          "percent": null,
          "description": null,
          "minZoom": null,
          "maxZoom": null,
          "tooltip": "hover"
        }
      ],
      "overlays": [],
      "shapes": [],
      "files": [
        "Lieux/Jérusalem.md"
      ]
    }
  ],
  "defaultMarker": {
    "type": "default",
    "iconName": "map-marker",
    "color": "#dddddd",
    "transform": {
      "size": 6,
      "x": 0,
      "y": -2
    }
  },
  "markerIcons": [
    {
      "type": "laboratoire",
      "iconName": "clinic-medical",
      "color": "#bd0000",
      "alpha": 1,
      "layer": false,
      "transform": {
        "size": 6,
        "x": 0,
        "y": -2
      },
      "isImage": false,
      "tags": [],
      "minZoom": null,
      "maxZoom": null
    },
    {
      "type": "Bar",
      "iconName": "beer",
      "color": "#cc9600",
      "alpha": 1,
      "layer": false,
      "transform": {
        "size": 6,
        "x": 0,
        "y": -2
      },
      "isImage": false,
      "tags": [],
      "minZoom": null,
      "maxZoom": null
    },
    {
      "type": "Maison",
      "iconName": "home",
      "color": "#dddddd",
      "alpha": 1,
      "layer": false,
      "transform": {
        "size": 6,
        "x": 0,
        "y": -2
      },
      "isImage": false,
      "tags": [],
      "minZoom": null,
      "maxZoom": null
    },
    {
      "type": "Appartement",
      "iconName": "building",
      "color": "#dddddd",
      "alpha": 1,
      "layer": false,
      "transform": {
        "size": 6,
        "x": 0,
        "y": -2
      },
      "isImage": false,
      "tags": [],
      "minZoom": null,
      "maxZoom": null
    },
    {
      "type": "fealand",
      "iconName": "landmark",
      "color": "#dddddd",
      "alpha": 1,
      "layer": false,
      "transform": {
        "size": 6,
        "x": 0,
        "y": -2
      },
      "isImage": false,
      "tags": [],
      "minZoom": null,
      "maxZoom": null
    },
    {
      "type": "bomb",
      "iconName": "bomb",
      "color": "#dddddd",
      "alpha": 1,
      "layer": false,
      "transform": {
        "size": 6,
        "x": 0,
        "y": -2
      },
      "isImage": false,
      "tags": [],
      "minZoom": null,
      "maxZoom": null
    },
    {
      "type": "People",
      "iconName": "male",
      "color": "#dddddd",
      "alpha": 1,
      "layer": false,
      "transform": {
        "size": 6,
        "x": 0,
        "y": -2
      },
      "isImage": false,
      "tags": [],
      "minZoom": null,
      "maxZoom": null
    }
  ],
  "color": "#dddddd",
  "lat": 39.983334,
  "long": -82.98333,
  "notePreview": false,
  "layerMarkers": true,
  "previousVersion": "6.0.5",
  "version": {
    "major": 6,
    "minor": 0,
    "patch": 5
  },
  "warnedAboutMapMarker": false,
  "copyOnClick": false,
  "displayMarkerTooltips": "hover",
  "displayOverlayTooltips": true,
  "configDirectory": null,
  "mapViewEnabled": true,
  "mapViewParameters": {},
  "enableDraw": true,
  "defaultUnitType": "imperial",
  "defaultTile": "https://{s}.basemaps.cartocdn.com/rastertiles/voyager/{z}/{x}/{y}.png",
  "defaultTileDark": "https://{s}.basemaps.cartocdn.com/rastertiles/voyager/{z}/{x}/{y}.png",
  "defaultAttribution": "&copy; <a href=\"https://www.openstreetmap.org/copyright\">OpenStreetMap</a> contributors &copy; <a href=\"https://carto.com/attributions\">CARTO</a>",
  "defaultTileSubdomains": "a,b,c,d"
}